<Properties StartupConfiguration="{3B23A723-A540-483A-BB4C-A74797366832}|Default">
  <MultiItemStartupConfigurations />
  <MonoDevelop.Ide.ItemProperties.ServiceBusQueue PreferredExecutionTarget="MonoDevelop.Default" />
  <MonoDevelop.Ide.Workbench ActiveDocument="ServiceBusQueue/Program.cs">
    <Files>
      <File FileName="ServiceBusQueue/Program.cs" Line="68" Column="1" />
      <File FileName="ServiceBusQueue/Order.cs" Line="14" Column="1" />
    </Files>
    <Pads>
      <Pad Id="ProjectPad">
        <State name="__root__">
          <Node name="ServiceBusQueue" expanded="True">
            <Node name="ServiceBusQueue" expanded="True" />
          </Node>
        </State>
      </Pad>
      <Pad Id="MonoDevelop.Debugger.WatchPad">
        <State />
      </Pad>
    </Pads>
  </MonoDevelop.Ide.Workbench>
  <MonoDevelop.Ide.DebuggingService.Breakpoints>
    <BreakpointStore />
  </MonoDevelop.Ide.DebuggingService.Breakpoints>
  <MonoDevelop.Ide.DebuggingService.PinnedWatches />
  <MonoDevelop.Ide.Workspace ActiveConfiguration="Debug" />
</Properties>